search_engine_cpp/__init__.py
search_engine_cpp/_inverted_index.pyi
search_engine_cpp/_page_rank.pyi
search_engine_cpp/crawler.py
search_engine_cpp/exceptions.py
search_engine_cpp/helper/__init__.py
search_engine_cpp/helper/converter.py
search_engine_cpp/preprocessing/stemmer_cpp.pyi
search_engine_cpp/wrapper/__init__.py
search_engine_cpp/wrapper/inverted_index/__init__.py
search_engine_cpp/wrapper/page_rank/__init__.py
search_engine_cpp/_hello.cpython-311-x86_64-linux-gnu.so
search_engine_cpp/_inverted_index.cpython-311-x86_64-linux-gnu.so
search_engine_cpp/_page_rank.cpython-311-x86_64-linux-gnu.so
search_engine_cpp/preprocessing/stemmer_cpp.cpython-311-x86_64-linux-gnu.so
search_engine_cpp-0.2.0.dist-info/LICENSE.md
search_engine_cpp-0.2.0.dist-info/METADATA
search_engine_cpp-0.2.0.dist-info/WHEEL
search_engine_cpp-0.2.0.dist-info/RECORD
