Metadata-Version: 2.3
Name: search-engine-cpp
Version: 0.2.0
Summary: Search Engine is a project that implements a basic search engine using C++, Python, and Cython. It builds a reverse index and ranks pages with the PageRank algorithm based on keyword relevance and page importance.
License: MIT
Author: Pedro Bianchini de Quadros
Author-email: pedrobiqua@gmail.com
Requires-Python: >=3.10,<4.0
Classifier: License :: OSI Approved :: MIT License
Classifier: Programming Language :: Python :: 3
Classifier: Programming Language :: Python :: 3.10
Classifier: Programming Language :: Python :: 3.11
Classifier: Programming Language :: Python :: 3.12
Classifier: Programming Language :: Python :: 3.13
Requires-Dist: beautifulsoup4 (>=4.12.3,<5.0.0)
Requires-Dist: cython (>=3.0.11,<4.0.0)
Requires-Dist: requests (>=2.32.3,<3.0.0)
Project-URL: Documentation, https://bianchtech.github.io/Search_Engine/html/Chap_00_Architecture_documentation.html
Project-URL: Homepage, https://pedrobiqua.github.io/Search_Engine/html/
Project-URL: Repository, https://github.com/BianchTech/Search_Engine
